sibyl/__init__.py
sibyl/config.py
sibyl/transforms.py
sibyl/utils.py
sibyl/transformations/__init__.py
sibyl/transformations/utils.py
sibyl/transformations/image/__init__.py
sibyl/transformations/text/__init__.py
sibyl/transformations/text/abstract_batch_transformation.py
sibyl/transformations/text/abstract_transformation.py
sibyl/transformations/text/tasks.py
sibyl/transformations/text/contraction/__init__.py
sibyl/transformations/text/contraction/contract_contractions.py
sibyl/transformations/text/contraction/expand_contractions.py
sibyl/transformations/text/data/__init__.py
sibyl/transformations/text/data/locations.py
sibyl/transformations/text/data/persons.py
sibyl/transformations/text/data/phrases.py
sibyl/transformations/text/data/opinion-lexicon-English/__init__.py
sibyl/transformations/text/data/opinion-lexicon-English/negative-words.txt
sibyl/transformations/text/data/opinion-lexicon-English/positive-words.txt
sibyl/transformations/text/emoji/__init__.py
sibyl/transformations/text/emoji/demojify.py
sibyl/transformations/text/emoji/emojify.py
sibyl/transformations/text/entities/__init__.py
sibyl/transformations/text/entities/change_location.py
sibyl/transformations/text/entities/change_name.py
sibyl/transformations/text/generative/__init__.py
sibyl/transformations/text/generative/concept2sentence.py
sibyl/transformations/text/generative/explainer.py
sibyl/transformations/text/generative/sequence_classification.py
sibyl/transformations/text/insertion/__init__.py
sibyl/transformations/text/insertion/insert_punctuation_marks.py
sibyl/transformations/text/insertion/random_insertion.py
sibyl/transformations/text/insertion/sentiment_phrase.py
sibyl/transformations/text/links/__init__.py
sibyl/transformations/text/links/add_sentiment_link.py
sibyl/transformations/text/links/import_link_text.py
sibyl/transformations/text/mixture/__init__.py
sibyl/transformations/text/mixture/concept_mix.py
sibyl/transformations/text/mixture/text_mix.py
sibyl_tool-0.1.11.dist-info/LICENSE
sibyl_tool-0.1.11.dist-info/METADATA
sibyl_tool-0.1.11.dist-info/WHEEL
sibyl_tool-0.1.11.dist-info/top_level.txt
sibyl_tool-0.1.11.dist-info/RECORD
