Metadata-Version: 2.1
Name: sibyl-tool
Version: 0.1.11
Summary: A tool for sibylvariant transformations
Home-page: https://github.com/fabriceyhc/Sibyl
Author: Fabrice Harel-Canada
Author-email: fabriceyhc@gmail.com
Project-URL: Bug Tracker, https://github.com/fabriceyhc/Sibyl/issues
Classifier: Programming Language :: Python :: 3
Classifier: License :: OSI Approved :: MIT License
Classifier: Operating System :: OS Independent
Requires-Python: >=3.6
License-File: LICENSE
Requires-Dist: emoji-translate
Requires-Dist: pattern
Requires-Dist: transformers-interpret
Requires-Dist: pke-tool
